mklib_models/__about__.py
mklib_models/__init__.py
mklib_models/__main__.py
madskris_mklib_models-0.0.1.dist-info/METADATA
madskris_mklib_models-0.0.1.dist-info/WHEEL
madskris_mklib_models-0.0.1.dist-info/licenses/LICENSE.txt
madskris_mklib_models-0.0.1.dist-info/RECORD
