Metadata-Version: 2.3
Name: madskris.mklib-models
Version: 0.0.1
Author-email: Mads Kristensen <madskris@proton.me>
License-Expression: MIT
License-File: LICENSE.txt
Classifier: Programming Language :: Python :: 3.12
Classifier: Programming Language :: Python :: Implementation :: CPython
Classifier: Programming Language :: Python :: Implementation :: PyPy
Requires-Python: >=3.12
Requires-Dist: attrs
